seamm_widgets/__init__.py
seamm_widgets/_version.py
seamm_widgets/check_tree.py
seamm_widgets/html_widgets.py
seamm_widgets/keywords.py
seamm_widgets/labeled_combobox.py
seamm_widgets/labeled_entry.py
seamm_widgets/labeled_widget.py
seamm_widgets/mousewheel_support.py
seamm_widgets/periodic_table.py
seamm_widgets/property_table.py
seamm_widgets/scrolled_columns.py
seamm_widgets/scrolled_frame.py
seamm_widgets/scrolled_labelframe.py
seamm_widgets/search_criteria.py
seamm_widgets/unit_combobox.py
seamm_widgets/unit_entry.py
seamm_widgets/data/checked.png
seamm_widgets/data/mixed.png
seamm_widgets/data/unchecked.png
seamm_widgets-2025.10.22.dist-info/licenses/AUTHORS.rst
seamm_widgets-2025.10.22.dist-info/licenses/LICENSE
seamm_widgets-2025.10.22.dist-info/METADATA
seamm_widgets-2025.10.22.dist-info/WHEEL
seamm_widgets-2025.10.22.dist-info/top_level.txt
seamm_widgets-2025.10.22.dist-info/RECORD
